acrome_smd_beta-0.0.4.dist-info/licenses/LICENSE
smd/SMD_device.py
smd/__init__.py
smd/blue.py
smd/green.py
smd/red.py
smd/serial_port.py
acrome_smd_beta-0.0.4.dist-info/METADATA
acrome_smd_beta-0.0.4.dist-info/WHEEL
acrome_smd_beta-0.0.4.dist-info/top_level.txt
acrome_smd_beta-0.0.4.dist-info/RECORD
